Metadata-Version: 1.0
Name: quantly
Version: 0.1.2
Summary: A multi-tool financial suite for equity traders.
Home-page: https://github.com/BluechipData/quantly
Author: Brandon Boisvert
Author-email: UNKNOWN
License: MIT
Platform: UNKNOWN
